p_privacy_metadata/ELA.py
p_privacy_metadata/__init__.py
p_privacy_metadata/privacyExtension.py
p_privacy_metadata-0.0.5.dist-info/LICENSE
p_privacy_metadata-0.0.5.dist-info/METADATA
p_privacy_metadata-0.0.5.dist-info/WHEEL
p_privacy_metadata-0.0.5.dist-info/pbr.json
p_privacy_metadata-0.0.5.dist-info/top_level.txt
p_privacy_metadata-0.0.5.dist-info/RECORD
